{ 
	"question": "[{
		\"img\":\"\",
		\"question\":\"假如，你正在看鬼片，你觉得片中的鬼最有可能最先出现在哪里？\",
		\"answer\":{\"a\":{\"title\":\"厕所\",
		\"next\":\"A\"},
		\"b\":{\"title\":\"桌子底下\",
		\"next\":\"B\"},
		\"c\":{\"title\":\"储物室\",
		\"next\":\"C\"},
		\"d\":{\"title\":\"电梯\",
		\"next\":\"D\"},
		\"e\":{\"title\":\"办公室\",
		\"next\":\"E\"}}}]", 
	"result": 
		"[{\"threshold\":\"A\",
			\"img\":\"\",
			\"title\":\"忠诚度55%\",
			\"desc\":\"你的忠诚程度颇有相对论性质，你会觉得大家礼尚往来嘛。如果对方对你好，则万事都好商量，如果对方总是对你有所保留的话，你当然在心中也会留下问号，想着那就要看看情况再说。\",
			\"sharetitle\":\"我的爱情忠诚度55％，测测看你对爱情的忠诚度有多高？
		\"},{\"threshold\":\"B\",
			\"img\":\"\",
			\"title\":\"忠诚度30%\",
			\"desc\":\"唉！在爱情上，你可以说是个花心大萝卜，谈不上什么忠诚度可言，一有新的猎物出现，你的心就跑了；在工作上也是如此，如果正好工作上出现了什么困难，而外界又有些不错的利益诱惑时，你犯下错误的机率颇高。\",
			\"sharetitle\":\"我的爱情忠诚度30％，测测看你对爱情的忠诚度有多高？
		\"},{\"threshold\":\"C\",
			\"img\":\"\",
			\"title\":\"忠诚度99%\",
			\"desc\":\"现在这样的人真是难找啊！真不知道该说你傻还是呆。你的伴侣和朋友遇到了你真是他们的福气。不过有时候人心难测，你一定要先看清楚对象，不然小心遭人利用哦。\",
			\"sharetitle\":\"我的爱情忠诚度99％，测测看你对爱情的忠诚度有多高？
		\"},{\"threshold\":\"D\",
			\"img\":\"\",
			\"title\":\"忠诚度80%\",
			\"desc\":\"你的态度是那种认定了就不会改变的。不过当你认定对方之前，当然也是有种种考虑与观察的，当你开始觉得这个人很值得做你的恋人或者朋友时，你会心甘情愿的为对方付出，一切力挺到底。\",
			\"sharetitle\":\"我的爱情忠诚度80％，测测看你对爱情的忠诚度有多高？
		\"},{\"threshold\":\"E\",
			\"img\":\"\",
			\"title\":\"忠诚度20%\",
			\"desc\":\"利益会是你最大的考量，当对方没有利用价值，或没达到你的要求、标準时，你会毫不犹疑，转身走人。虽然说你对别人不忠诚，但你却是一个要求别人100%对你忠诚的人！\",
			\"sharetitle\":\"我的爱情忠诚度20％，测测看你对爱情的忠诚度有多高？
		\"}]" 
};
